openwrapper.py
openwrapper-0.2.0.dist-info/licenses/LICENSE
openwrapper-0.2.0.dist-info/METADATA
openwrapper-0.2.0.dist-info/WHEEL
openwrapper-0.2.0.dist-info/top_level.txt
openwrapper-0.2.0.dist-info/RECORD
