Metadata-Version: 2.4
Name: openwrapper
Version: 0.2.0
Summary: Discord API wrapper
Author: dataopen
Project-URL: Homepage, https://github.com/dataopen/openwrapper
Project-URL: Issues, https://discord.gg/opening
License-File: LICENSE
Requires-Dist: requests
Dynamic: license-file
